drawilleplot/__init__.py
drawilleplot-0.1.0.dist-info/DESCRIPTION.rst
drawilleplot-0.1.0.dist-info/METADATA
drawilleplot-0.1.0.dist-info/RECORD
drawilleplot-0.1.0.dist-info/WHEEL
drawilleplot-0.1.0.dist-info/metadata.json
drawilleplot-0.1.0.dist-info/top_level.txt
